unifair/__init__.py
unifair/compute/__init__.py
unifair/compute/flow.py
unifair/compute/job.py
unifair/compute/task.py
unifair/config/__init__.py
unifair/config/engine.py
unifair/config/publisher.py
unifair/config/registry.py
unifair/config/runtime.py
unifair/data/__init__.py
unifair/data/dataset.py
unifair/data/model.py
unifair/data/serializer.py
unifair/engine/__init__.py
unifair/engine/base.py
unifair/engine/constants.py
unifair/engine/job_runner.py
unifair/engine/local.py
unifair/engine/prefect.py
unifair/engine/protocols.py
unifair/engine/registry.py
unifair/modules/__init__.py
unifair/modules/fairtracks/__init__.py
unifair/modules/fairtracks/functions.py
unifair/modules/fairtracks/tasks.py
unifair/modules/general/__init__.py
unifair/modules/general/tasks.py
unifair/modules/json/__init__.py
unifair/modules/json/models.py
unifair/modules/json/serializers.py
unifair/modules/json/tasks.py
unifair/modules/json/util.py
unifair/modules/pandas/__init__.py
unifair/modules/pandas/models.py
unifair/modules/pandas/serializers.py
unifair/modules/pandas/tasks.py
unifair/modules/pandas/util.py
unifair/modules/raw/__init__.py
unifair/modules/raw/serializers.py
unifair/modules/raw/tasks.py
unifair/modules/raw/util.py
unifair/modules/tables/__init__.py
unifair/modules/tables/models.py
unifair/modules/tables/tasks.py
unifair/old/core/__init__.py
unifair/util/__init__.py
unifair/util/callable_decorator_cls.py
unifair/util/dataframe.py
unifair/util/helpers.py
unifair/util/param_key_mapper.py
unifair-0.1.0.dist-info/LICENSE
unifair-0.1.0.dist-info/WHEEL
unifair-0.1.0.dist-info/METADATA
unifair-0.1.0.dist-info/RECORD
