Metadata-Version: 2.1
Name: unifair
Version: 0.1.0
Summary: 
Author: Sveinung Gundersen
Author-email: sveinugu@gmail.com
Requires-Python: >=3.10,<4.0
Classifier: Programming Language :: Python :: 3
Classifier: Programming Language :: Python :: 3.10
Classifier: Programming Language :: Python :: 3.11
Requires-Dist: aiostream (>=0.4.5,<0.5.0)
Requires-Dist: greenlet (>=2.0.1,<3.0.0)
Requires-Dist: inflection (>=0.5.1,<0.6.0)
Requires-Dist: jq (>=1.3.0,<2.0.0)
Requires-Dist: mypy (>=0.991,<0.992)
Requires-Dist: orjson (>=3.8.0,<4.0.0)
Requires-Dist: pandas (>=1.2.4,<2.0.0)
Requires-Dist: prefect (>=2.6.9,<3.0.0)
Requires-Dist: pydantic (>=1.10.2,<2.0.0)
Requires-Dist: pytest-asyncio (>=0.20.2,<0.21.0)
Requires-Dist: pytest-cases (>=3.6.13,<4.0.0)
Requires-Dist: python-slugify (>=7.0.0,<8.0.0)
Requires-Dist: requests (>=2.25.1,<3.0.0)
